{
  "success": true,
  "error": null,
  "results": {
    "detectors": [
      {
        "elements": [
          {
            "type": "function",
            "name": "verify",
            "source_mapping": {
              "start": 2693,
              "length": 830,
              "filename_relative": "crytic-export/etherscan-contracts/0x5b8aea7132b22bc795f1289a389250860d6353b2-LoopyFriends.sol",
              "filename_absolute": "/mnt/c/Users/zzs/Desktop/CrySol_Static/crytic-export/etherscan-contracts/0x5b8aea7132b22bc795f1289a389250860d6353b2-LoopyFriends.sol",
              "filename_short": "crytic-export/etherscan-contracts/0x5b8aea7132b22bc795f1289a389250860d6353b2-LoopyFriends.sol",
              "is_dependency": false,
              "lines": [
                33,
                34,
                35,
                36,
                37,
                38,
                39,
                40,
                41,
                42,
                43,
                44,
                45,
                46,
                47,
                48,
                49,
                50,
                51,
                52,
                53,
                54
              ],
              "starting_column": 5,
              "ending_column": 6
            },
            "type_specific_fields": {
              "parent": {
                "type": "contract",
                "name": "MerkleProof",
                "source_mapping": {
                  "start": 2332,
                  "length": 1194,
                  "filename_relative": "crytic-export/etherscan-contracts/0x5b8aea7132b22bc795f1289a389250860d6353b2-LoopyFriends.sol",
                  "filename_absolute": "/mnt/c/Users/zzs/Desktop/CrySol_Static/crytic-export/etherscan-contracts/0x5b8aea7132b22bc795f1289a389250860d6353b2-LoopyFriends.sol",
                  "filename_short": "crytic-export/etherscan-contracts/0x5b8aea7132b22bc795f1289a389250860d6353b2-LoopyFriends.sol",
                  "is_dependency": false,
                  "lines": [
                    26,
                    27,
                    28,
                    29,
                    30,
                    31,
                    32,
                    33,
                    34,
                    35,
                    36,
                    37,
                    38,
                    39,
                    40,
                    41,
                    42,
                    43,
                    44,
                    45,
                    46,
                    47,
                    48,
                    49,
                    50,
                    51,
                    52,
                    53,
                    54,
                    55
                  ],
                  "starting_column": 1,
                  "ending_column": 2
                }
              },
              "signature": "verify(bytes32[],bytes32,bytes32)"
            }
          }
        ],
        "description": "MerkleProof.verify(bytes32[],bytes32,bytes32) (crytic-export/etherscan-contracts/0x5b8aea7132b22bc795f1289a389250860d6353b2-LoopyFriends.sol#33-54) uses keccak256(bytes)\n",
        "markdown": "[MerkleProof.verify(bytes32[],bytes32,bytes32)](crytic-export/etherscan-contracts/0x5b8aea7132b22bc795f1289a389250860d6353b2-LoopyFriends.sol#L33-L54) uses keccak256(bytes)\n",
        "first_markdown_element": "crytic-export/etherscan-contracts/0x5b8aea7132b22bc795f1289a389250860d6353b2-LoopyFriends.sol#L33-L54",
        "id": "391c199dde778baadc407fd4e0b424d21af0e5bcbcca142bf95097bc7b380e31",
        "check": "crypto",
        "impact": "High",
        "confidence": "High"
      }
    ]
  }
}