{
  "success": true,
  "error": null,
  "results": {
    "detectors": [
      {
        "elements": [
          {
            "type": "function",
            "name": "generateMetadataHash",
            "source_mapping": {
              "start": 2861,
              "length": 509,
              "filename_relative": "crytic-export/etherscan-contracts/0x88cf4d065f9d1578239d5c5020c24aec16789034-ClayStake/contracts/ClayGen.sol",
              "filename_absolute": "/mnt/c/Users/zzs/Desktop/CrySol_Static/crytic-export/etherscan-contracts/0x88cf4d065f9d1578239d5c5020c24aec16789034-ClayStake/contracts/ClayGen.sol",
              "filename_short": "contracts/ClayGen.sol",
              "is_dependency": false,
              "lines": [
                116,
                117,
                118,
                119,
                120,
                121,
                122,
                123,
                124,
                125,
                126,
                127,
                128,
                129,
                130,
                131,
                132,
                133
              ],
              "starting_column": 5,
              "ending_column": 6
            },
            "type_specific_fields": {
              "parent": {
                "type": "contract",
                "name": "ClayGen",
                "source_mapping": {
                  "start": 271,
                  "length": 5087,
                  "filename_relative": "crytic-export/etherscan-contracts/0x88cf4d065f9d1578239d5c5020c24aec16789034-ClayStake/contracts/ClayGen.sol",
                  "filename_absolute": "/mnt/c/Users/zzs/Desktop/CrySol_Static/crytic-export/etherscan-contracts/0x88cf4d065f9d1578239d5c5020c24aec16789034-ClayStake/contracts/ClayGen.sol",
                  "filename_short": "contracts/ClayGen.sol",
                  "is_dependency": false,
                  "lines": [
                    10,
                    11,
                    12,
                    13,
                    14,
                    15,
                    16,
                    17,
                    18,
                    19,
                    20,
                    21,
                    22,
                    23,
                    24,
                    25,
                    26,
                    27,
                    28,
                    29,
                    30,
                    31,
                    32,
                    33,
                    34,
                    35,
                    36,
                    37,
                    38,
                    39,
                    40,
                    41,
                    42,
                    43,
                    44,
                    45,
                    46,
                    47,
                    48,
                    49,
                    50,
                    51,
                    52,
                    53,
                    54,
                    55,
                    56,
                    57,
                    58,
                    59,
                    60,
                    61,
                    62,
                    63,
                    64,
                    65,
                    66,
                    67,
                    68,
                    69,
                    70,
                    71,
                    72,
                    73,
                    74,
                    75,
                    76,
                    77,
                    78,
                    79,
                    80,
                    81,
                    82,
                    83,
                    84,
                    85,
                    86,
                    87,
                    88,
                    89,
                    90,
                    91,
                    92,
                    93,
                    94,
                    95,
                    96,
                    97,
                    98,
                    99,
                    100,
                    101,
                    102,
                    103,
                    104,
                    105,
                    106,
                    107,
                    108,
                    109,
                    110,
                    111,
                    112,
                    113,
                    114,
                    115,
                    116,
                    117,
                    118,
                    119,
                    120,
                    121,
                    122,
                    123,
                    124,
                    125,
                    126,
                    127,
                    128,
                    129,
                    130,
                    131,
                    132,
                    133,
                    134,
                    135,
                    136,
                    137,
                    138,
                    139,
                    140,
                    141,
                    142,
                    143,
                    144,
                    145,
                    146,
                    147,
                    148,
                    149,
                    150,
                    151,
                    152,
                    153,
                    154,
                    155,
                    156,
                    157,
                    158,
                    159,
                    160,
                    161,
                    162,
                    163,
                    164,
                    165,
                    166,
                    167,
                    168,
                    169,
                    170,
                    171,
                    172,
                    173,
                    174,
                    175,
                    176,
                    177,
                    178,
                    179,
                    180,
                    181,
                    182,
                    183,
                    184,
                    185,
                    186,
                    187,
                    188,
                    189,
                    190,
                    191
                  ],
                  "starting_column": 1,
                  "ending_column": 2
                }
              },
              "signature": "generateMetadataHash(uint256,uint256)"
            }
          }
        ],
        "description": "ClayGen.generateMetadataHash(uint256,uint256) (contracts/ClayGen.sol#116-133) uses keccak256(bytes)\n",
        "markdown": "[ClayGen.generateMetadataHash(uint256,uint256)](crytic-export/etherscan-contracts/0x88cf4d065f9d1578239d5c5020c24aec16789034-ClayStake/contracts/ClayGen.sol#L116-L133) uses keccak256(bytes)\n",
        "first_markdown_element": "crytic-export/etherscan-contracts/0x88cf4d065f9d1578239d5c5020c24aec16789034-ClayStake/contracts/ClayGen.sol#L116-L133",
        "id": "44b05909fb9bc40cd76dd131817801b84213f53d476f95071a65a31954ccfe98",
        "check": "crypto",
        "impact": "High",
        "confidence": "High"
      },
      {
        "elements": [
          {
            "type": "function",
            "name": "renderAttributesFromHash",
            "source_mapping": {
              "start": 3995,
              "length": 1144,
              "filename_relative": "crytic-export/etherscan-contracts/0x88cf4d065f9d1578239d5c5020c24aec16789034-ClayStake/contracts/ClayGen.sol",
              "filename_absolute": "/mnt/c/Users/zzs/Desktop/CrySol_Static/crytic-export/etherscan-contracts/0x88cf4d065f9d1578239d5c5020c24aec16789034-ClayStake/contracts/ClayGen.sol",
              "filename_short": "contracts/ClayGen.sol",
              "is_dependency": false,
              "lines": [
                154,
                155,
                156,
                157,
                158,
                159,
                160,
                161,
                162,
                163,
                164,
                165,
                166,
                167,
                168,
                169,
                170,
                171,
                172,
                173,
                174,
                175,
                176,
                177,
                178,
                179,
                180,
                181,
                182,
                183,
                184,
                185
              ],
              "starting_column": 5,
              "ending_column": 6
            },
            "type_specific_fields": {
              "parent": {
                "type": "contract",
                "name": "ClayGen",
                "source_mapping": {
                  "start": 271,
                  "length": 5087,
                  "filename_relative": "crytic-export/etherscan-contracts/0x88cf4d065f9d1578239d5c5020c24aec16789034-ClayStake/contracts/ClayGen.sol",
                  "filename_absolute": "/mnt/c/Users/zzs/Desktop/CrySol_Static/crytic-export/etherscan-contracts/0x88cf4d065f9d1578239d5c5020c24aec16789034-ClayStake/contracts/ClayGen.sol",
                  "filename_short": "contracts/ClayGen.sol",
                  "is_dependency": false,
                  "lines": [
                    10,
                    11,
                    12,
                    13,
                    14,
                    15,
                    16,
                    17,
                    18,
                    19,
                    20,
                    21,
                    22,
                    23,
                    24,
                    25,
                    26,
                    27,
                    28,
                    29,
                    30,
                    31,
                    32,
                    33,
                    34,
                    35,
                    36,
                    37,
                    38,
                    39,
                    40,
                    41,
                    42,
                    43,
                    44,
                    45,
                    46,
                    47,
                    48,
                    49,
                    50,
                    51,
                    52,
                    53,
                    54,
                    55,
                    56,
                    57,
                    58,
                    59,
                    60,
                    61,
                    62,
                    63,
                    64,
                    65,
                    66,
                    67,
                    68,
                    69,
                    70,
                    71,
                    72,
                    73,
                    74,
                    75,
                    76,
                    77,
                    78,
                    79,
                    80,
                    81,
                    82,
                    83,
                    84,
                    85,
                    86,
                    87,
                    88,
                    89,
                    90,
                    91,
                    92,
                    93,
                    94,
                    95,
                    96,
                    97,
                    98,
                    99,
                    100,
                    101,
                    102,
                    103,
                    104,
                    105,
                    106,
                    107,
                    108,
                    109,
                    110,
                    111,
                    112,
                    113,
                    114,
                    115,
                    116,
                    117,
                    118,
                    119,
                    120,
                    121,
                    122,
                    123,
                    124,
                    125,
                    126,
                    127,
                    128,
                    129,
                    130,
                    131,
                    132,
                    133,
                    134,
                    135,
                    136,
                    137,
                    138,
                    139,
                    140,
                    141,
                    142,
                    143,
                    144,
                    145,
                    146,
                    147,
                    148,
                    149,
                    150,
                    151,
                    152,
                    153,
                    154,
                    155,
                    156,
                    157,
                    158,
                    159,
                    160,
                    161,
                    162,
                    163,
                    164,
                    165,
                    166,
                    167,
                    168,
                    169,
                    170,
                    171,
                    172,
                    173,
                    174,
                    175,
                    176,
                    177,
                    178,
                    179,
                    180,
                    181,
                    182,
                    183,
                    184,
                    185,
                    186,
                    187,
                    188,
                    189,
                    190,
                    191
                  ],
                  "starting_column": 1,
                  "ending_column": 2
                }
              },
              "signature": "renderAttributesFromHash(string,uint256)"
            }
          }
        ],
        "description": "ClayGen.renderAttributesFromHash(string,uint256) (contracts/ClayGen.sol#154-185) uses keccak256(bytes)\n",
        "markdown": "[ClayGen.renderAttributesFromHash(string,uint256)](crytic-export/etherscan-contracts/0x88cf4d065f9d1578239d5c5020c24aec16789034-ClayStake/contracts/ClayGen.sol#L154-L185) uses keccak256(bytes)\n",
        "first_markdown_element": "crytic-export/etherscan-contracts/0x88cf4d065f9d1578239d5c5020c24aec16789034-ClayStake/contracts/ClayGen.sol#L154-L185",
        "id": "849c046a06e253dcdbfb0814a1e3022b065a8723b979215ffe96ae4f13a63871",
        "check": "crypto",
        "impact": "High",
        "confidence": "High"
      },
      {
        "elements": [
          {
            "type": "function",
            "name": "generateMetadataHash",
            "source_mapping": {
              "start": 2014,
              "length": 479,
              "filename_relative": "crytic-export/etherscan-contracts/0x88cf4d065f9d1578239d5c5020c24aec16789034-ClayStake/contracts/ClayLibrary.sol",
              "filename_absolute": "/mnt/c/Users/zzs/Desktop/CrySol_Static/crytic-export/etherscan-contracts/0x88cf4d065f9d1578239d5c5020c24aec16789034-ClayStake/contracts/ClayLibrary.sol",
              "filename_short": "contracts/ClayLibrary.sol",
              "is_dependency": false,
              "lines": [
                88,
                89,
                90,
                91,
                92,
                93,
                94,
                95,
                96,
                97,
                98,
                99,
                100,
                101,
                102,
                103,
                104,
                105
              ],
              "starting_column": 5,
              "ending_column": 6
            },
            "type_specific_fields": {
              "parent": {
                "type": "contract",
                "name": "ClayLibrary",
                "source_mapping": {
                  "start": 242,
                  "length": 4636,
                  "filename_relative": "crytic-export/etherscan-contracts/0x88cf4d065f9d1578239d5c5020c24aec16789034-ClayStake/contracts/ClayLibrary.sol",
                  "filename_absolute": "/mnt/c/Users/zzs/Desktop/CrySol_Static/crytic-export/etherscan-contracts/0x88cf4d065f9d1578239d5c5020c24aec16789034-ClayStake/contracts/ClayLibrary.sol",
                  "filename_short": "contracts/ClayLibrary.sol",
                  "is_dependency": false,
                  "lines": [
                    9,
                    10,
                    11,
                    12,
                    13,
                    14,
                    15,
                    16,
                    17,
                    18,
                    19,
                    20,
                    21,
                    22,
                    23,
                    24,
                    25,
                    26,
                    27,
                    28,
                    29,
                    30,
                    31,
                    32,
                    33,
                    34,
                    35,
                    36,
                    37,
                    38,
                    39,
                    40,
                    41,
                    42,
                    43,
                    44,
                    45,
                    46,
                    47,
                    48,
                    49,
                    50,
                    51,
                    52,
                    53,
                    54,
                    55,
                    56,
                    57,
                    58,
                    59,
                    60,
                    61,
                    62,
                    63,
                    64,
                    65,
                    66,
                    67,
                    68,
                    69,
                    70,
                    71,
                    72,
                    73,
                    74,
                    75,
                    76,
                    77,
                    78,
                    79,
                    80,
                    81,
                    82,
                    83,
                    84,
                    85,
                    86,
                    87,
                    88,
                    89,
                    90,
                    91,
                    92,
                    93,
                    94,
                    95,
                    96,
                    97,
                    98,
                    99,
                    100,
                    101,
                    102,
                    103,
                    104,
                    105,
                    106,
                    107,
                    108,
                    109,
                    110,
                    111,
                    112,
                    113,
                    114,
                    115,
                    116,
                    117,
                    118,
                    119,
                    120,
                    121,
                    122,
                    123,
                    124,
                    125,
                    126,
                    127,
                    128,
                    129,
                    130,
                    131,
                    132,
                    133,
                    134,
                    135,
                    136,
                    137,
                    138,
                    139,
                    140,
                    141,
                    142,
                    143,
                    144,
                    145,
                    146,
                    147,
                    148,
                    149,
                    150,
                    151,
                    152,
                    153,
                    154,
                    155,
                    156,
                    157,
                    158,
                    159,
                    160,
                    161,
                    162,
                    163,
                    164,
                    165,
                    166,
                    167,
                    168,
                    169,
                    170,
                    171,
                    172,
                    173,
                    174,
                    175,
                    176,
                    177,
                    178,
                    179,
                    180,
                    181,
                    182,
                    183,
                    184,
                    185,
                    186
                  ],
                  "starting_column": 1,
                  "ending_column": 2
                }
              },
              "signature": "generateMetadataHash(uint256)"
            }
          }
        ],
        "description": "ClayLibrary.generateMetadataHash(uint256) (contracts/ClayLibrary.sol#88-105) uses keccak256(bytes)\n",
        "markdown": "[ClayLibrary.generateMetadataHash(uint256)](crytic-export/etherscan-contracts/0x88cf4d065f9d1578239d5c5020c24aec16789034-ClayStake/contracts/ClayLibrary.sol#L88-L105) uses keccak256(bytes)\n",
        "first_markdown_element": "crytic-export/etherscan-contracts/0x88cf4d065f9d1578239d5c5020c24aec16789034-ClayStake/contracts/ClayLibrary.sol#L88-L105",
        "id": "bcca260395677559fde07b2f9a580d7b513229cece15ded7710ad7c939ef0aa2",
        "check": "crypto",
        "impact": "High",
        "confidence": "High"
      }
    ]
  }
}