{
  "success": true,
  "error": null,
  "results": {
    "detectors": [
      {
        "elements": [
          {
            "type": "function",
            "name": "constructor",
            "source_mapping": {
              "start": 1263,
              "length": 411,
              "filename_relative": "crytic-export/etherscan-contracts/0xb2e9c541cf2dbe0802f67668dcd6d728f888f4bd-APPLE/APPLE.sol",
              "filename_absolute": "/mnt/c/Users/zzs/Desktop/CrySol_Static/crytic-export/etherscan-contracts/0xb2e9c541cf2dbe0802f67668dcd6d728f888f4bd-APPLE/APPLE.sol",
              "filename_short": "APPLE.sol",
              "is_dependency": false,
              "lines": [
                42,
                43,
                44,
                45,
                46,
                47,
                48,
                49,
                50
              ],
              "starting_column": 5,
              "ending_column": 6
            },
            "type_specific_fields": {
              "parent": {
                "type": "contract",
                "name": "APPLE",
                "source_mapping": {
                  "start": 891,
                  "length": 1355,
                  "filename_relative": "crytic-export/etherscan-contracts/0xb2e9c541cf2dbe0802f67668dcd6d728f888f4bd-APPLE/APPLE.sol",
                  "filename_absolute": "/mnt/c/Users/zzs/Desktop/CrySol_Static/crytic-export/etherscan-contracts/0xb2e9c541cf2dbe0802f67668dcd6d728f888f4bd-APPLE/APPLE.sol",
                  "filename_short": "APPLE.sol",
                  "is_dependency": false,
                  "lines": [
                    28,
                    29,
                    30,
                    31,
                    32,
                    33,
                    34,
                    35,
                    36,
                    37,
                    38,
                    39,
                    40,
                    41,
                    42,
                    43,
                    44,
                    45,
                    46,
                    47,
                    48,
                    49,
                    50,
                    51,
                    52,
                    53,
                    54,
                    55,
                    56,
                    57,
                    58,
                    59,
                    60,
                    61,
                    62,
                    63,
                    64,
                    65,
                    66,
                    67,
                    68,
                    69,
                    70,
                    71
                  ],
                  "starting_column": 1,
                  "ending_column": 2
                }
              },
              "signature": "constructor(bytes,bytes)"
            }
          }
        ],
        "description": "APPLE.constructor(bytes,bytes) (APPLE.sol#42-50) uses keccak256(bytes)\n",
        "markdown": "[APPLE.constructor(bytes,bytes)](crytic-export/etherscan-contracts/0xb2e9c541cf2dbe0802f67668dcd6d728f888f4bd-APPLE/APPLE.sol#L42-L50) uses keccak256(bytes)\n",
        "first_markdown_element": "crytic-export/etherscan-contracts/0xb2e9c541cf2dbe0802f67668dcd6d728f888f4bd-APPLE/APPLE.sol#L42-L50",
        "id": "42759fad08e9cc203f0b32152967281e6bf10af20da56492c69dbf2ce439cd1e",
        "check": "crypto",
        "impact": "High",
        "confidence": "High"
      }
    ]
  }
}