{
  "success": true,
  "error": null,
  "results": {
    "detectors": [
      {
        "elements": [
          {
            "type": "function",
            "name": "whitelistMint",
            "source_mapping": {
              "start": 1866,
              "length": 582,
              "filename_relative": "crytic-export/etherscan-contracts/0xcf8bab4ac96c261fcd7a47b8a443fca4090b63cf-HempHeads/contracts/HempHeads.sol",
              "filename_absolute": "/mnt/c/Users/zzs/Desktop/CrySol_Static/crytic-export/etherscan-contracts/0xcf8bab4ac96c261fcd7a47b8a443fca4090b63cf-HempHeads/contracts/HempHeads.sol",
              "filename_short": "contracts/HempHeads.sol",
              "is_dependency": false,
              "lines": [
                62,
                63,
                64,
                65,
                66,
                67,
                68,
                69,
                70,
                71
              ],
              "starting_column": 3,
              "ending_column": 4
            },
            "type_specific_fields": {
              "parent": {
                "type": "contract",
                "name": "HempHeads",
                "source_mapping": {
                  "start": 595,
                  "length": 4702,
                  "filename_relative": "crytic-export/etherscan-contracts/0xcf8bab4ac96c261fcd7a47b8a443fca4090b63cf-HempHeads/contracts/HempHeads.sol",
                  "filename_absolute": "/mnt/c/Users/zzs/Desktop/CrySol_Static/crytic-export/etherscan-contracts/0xcf8bab4ac96c261fcd7a47b8a443fca4090b63cf-HempHeads/contracts/HempHeads.sol",
                  "filename_short": "contracts/HempHeads.sol",
                  "is_dependency": false,
                  "lines": [
                    18,
                    19,
                    20,
                    21,
                    22,
                    23,
                    24,
                    25,
                    26,
                    27,
                    28,
                    29,
                    30,
                    31,
                    32,
                    33,
                    34,
                    35,
                    36,
                    37,
                    38,
                    39,
                    40,
                    41,
                    42,
                    43,
                    44,
                    45,
                    46,
                    47,
                    48,
                    49,
                    50,
                    51,
                    52,
                    53,
                    54,
                    55,
                    56,
                    57,
                    58,
                    59,
                    60,
                    61,
                    62,
                    63,
                    64,
                    65,
                    66,
                    67,
                    68,
                    69,
                    70,
                    71,
                    72,
                    73,
                    74,
                    75,
                    76,
                    77,
                    78,
                    79,
                    80,
                    81,
                    82,
                    83,
                    84,
                    85,
                    86,
                    87,
                    88,
                    89,
                    90,
                    91,
                    92,
                    93,
                    94,
                    95,
                    96,
                    97,
                    98,
                    99,
                    100,
                    101,
                    102,
                    103,
                    104,
                    105,
                    106,
                    107,
                    108,
                    109,
                    110,
                    111,
                    112,
                    113,
                    114,
                    115,
                    116,
                    117,
                    118,
                    119,
                    120,
                    121,
                    122,
                    123,
                    124,
                    125,
                    126,
                    127,
                    128,
                    129,
                    130,
                    131,
                    132,
                    133,
                    134,
                    135,
                    136,
                    137,
                    138,
                    139,
                    140,
                    141,
                    142,
                    143,
                    144,
                    145,
                    146,
                    147,
                    148,
                    149,
                    150,
                    151,
                    152,
                    153,
                    154
                  ],
                  "starting_column": 1,
                  "ending_column": 2
                }
              },
              "signature": "whitelistMint(uint256,bytes32[])"
            }
          }
        ],
        "description": "HempHeads.whitelistMint(uint256,bytes32[]) (contracts/HempHeads.sol#62-71) uses keccak256(bytes)\n",
        "markdown": "[HempHeads.whitelistMint(uint256,bytes32[])](crytic-export/etherscan-contracts/0xcf8bab4ac96c261fcd7a47b8a443fca4090b63cf-HempHeads/contracts/HempHeads.sol#L62-L71) uses keccak256(bytes)\n",
        "first_markdown_element": "crytic-export/etherscan-contracts/0xcf8bab4ac96c261fcd7a47b8a443fca4090b63cf-HempHeads/contracts/HempHeads.sol#L62-L71",
        "id": "09f088578df2ab5445c42ca4b3af4243d9fe23591bf587ae585b1e2bc60056c8",
        "check": "crypto",
        "impact": "High",
        "confidence": "High"
      }
    ]
  }
}