{
  "success": true,
  "error": null,
  "results": {
    "detectors": [
      {
        "elements": [
          {
            "type": "function",
            "name": "getDomainSeparator",
            "source_mapping": {
              "start": 4157,
              "length": 178,
              "filename_relative": "crytic-export/etherscan-contracts/0xd34a24006b862f4e9936c506691539d6433ad297-AquaToken/contracts/AquaToken.sol",
              "filename_absolute": "/mnt/c/Users/zzs/Desktop/CrySol_Static/crytic-export/etherscan-contracts/0xd34a24006b862f4e9936c506691539d6433ad297-AquaToken/contracts/AquaToken.sol",
              "filename_short": "contracts/AquaToken.sol",
              "is_dependency": false,
              "lines": [
                108,
                109,
                110
              ],
              "starting_column": 5,
              "ending_column": 6
            },
            "type_specific_fields": {
              "parent": {
                "type": "contract",
                "name": "AquaToken",
                "source_mapping": {
                  "start": 433,
                  "length": 6780,
                  "filename_relative": "crytic-export/etherscan-contracts/0xd34a24006b862f4e9936c506691539d6433ad297-AquaToken/contracts/AquaToken.sol",
                  "filename_absolute": "/mnt/c/Users/zzs/Desktop/CrySol_Static/crytic-export/etherscan-contracts/0xd34a24006b862f4e9936c506691539d6433ad297-AquaToken/contracts/AquaToken.sol",
                  "filename_short": "contracts/AquaToken.sol",
                  "is_dependency": false,
                  "lines": [
                    13,
                    14,
                    15,
                    16,
                    17,
                    18,
                    19,
                    20,
                    21,
                    22,
                    23,
                    24,
                    25,
                    26,
                    27,
                    28,
                    29,
                    30,
                    31,
                    32,
                    33,
                    34,
                    35,
                    36,
                    37,
                    38,
                    39,
                    40,
                    41,
                    42,
                    43,
                    44,
                    45,
                    46,
                    47,
                    48,
                    49,
                    50,
                    51,
                    52,
                    53,
                    54,
                    55,
                    56,
                    57,
                    58,
                    59,
                    60,
                    61,
                    62,
                    63,
                    64,
                    65,
                    66,
                    67,
                    68,
                    69,
                    70,
                    71,
                    72,
                    73,
                    74,
                    75,
                    76,
                    77,
                    78,
                    79,
                    80,
                    81,
                    82,
                    83,
                    84,
                    85,
                    86,
                    87,
                    88,
                    89,
                    90,
                    91,
                    92,
                    93,
                    94,
                    95,
                    96,
                    97,
                    98,
                    99,
                    100,
                    101,
                    102,
                    103,
                    104,
                    105,
                    106,
                    107,
                    108,
                    109,
                    110,
                    111,
                    112,
                    113,
                    114,
                    115,
                    116,
                    117,
                    118,
                    119,
                    120,
                    121,
                    122,
                    123,
                    124,
                    125,
                    126,
                    127,
                    128,
                    129,
                    130,
                    131,
                    132,
                    133,
                    134,
                    135,
                    136,
                    137,
                    138,
                    139,
                    140,
                    141,
                    142,
                    143,
                    144,
                    145,
                    146,
                    147,
                    148,
                    149,
                    150,
                    151,
                    152,
                    153,
                    154,
                    155,
                    156,
                    157,
                    158,
                    159,
                    160,
                    161,
                    162,
                    163,
                    164,
                    165,
                    166,
                    167,
                    168,
                    169,
                    170,
                    171,
                    172,
                    173,
                    174,
                    175,
                    176,
                    177,
                    178,
                    179,
                    180,
                    181,
                    182,
                    183,
                    184,
                    185,
                    186,
                    187,
                    188,
                    189,
                    190,
                    191,
                    192,
                    193,
                    194,
                    195,
                    196,
                    197,
                    198,
                    199,
                    200
                  ],
                  "starting_column": 1,
                  "ending_column": 2
                }
              },
              "signature": "getDomainSeparator()"
            }
          }
        ],
        "description": "AquaToken.getDomainSeparator() (contracts/AquaToken.sol#108-110) uses keccak256(bytes)\n",
        "markdown": "[AquaToken.getDomainSeparator()](crytic-export/etherscan-contracts/0xd34a24006b862f4e9936c506691539d6433ad297-AquaToken/contracts/AquaToken.sol#L108-L110) uses keccak256(bytes)\n",
        "first_markdown_element": "crytic-export/etherscan-contracts/0xd34a24006b862f4e9936c506691539d6433ad297-AquaToken/contracts/AquaToken.sol#L108-L110",
        "id": "12514067b51488651eafece9bb189f1c61b0de179e559bef207f34ad8bc847a8",
        "check": "crypto",
        "impact": "High",
        "confidence": "High"
      },
      {
        "elements": [
          {
            "type": "function",
            "name": "permit",
            "source_mapping": {
              "start": 5834,
              "length": 524,
              "filename_relative": "crytic-export/etherscan-contracts/0xd34a24006b862f4e9936c506691539d6433ad297-AquaToken/contracts/AquaToken.sol",
              "filename_absolute": "/mnt/c/Users/zzs/Desktop/CrySol_Static/crytic-export/etherscan-contracts/0xd34a24006b862f4e9936c506691539d6433ad297-AquaToken/contracts/AquaToken.sol",
              "filename_short": "contracts/AquaToken.sol",
              "is_dependency": false,
              "lines": [
                157,
                158,
                159,
                160,
                161,
                162,
                163,
                164,
                165,
                166,
                167,
                168,
                169,
                170,
                171,
                172,
                173
              ],
              "starting_column": 5,
              "ending_column": 6
            },
            "type_specific_fields": {
              "parent": {
                "type": "contract",
                "name": "AquaToken",
                "source_mapping": {
                  "start": 433,
                  "length": 6780,
                  "filename_relative": "crytic-export/etherscan-contracts/0xd34a24006b862f4e9936c506691539d6433ad297-AquaToken/contracts/AquaToken.sol",
                  "filename_absolute": "/mnt/c/Users/zzs/Desktop/CrySol_Static/crytic-export/etherscan-contracts/0xd34a24006b862f4e9936c506691539d6433ad297-AquaToken/contracts/AquaToken.sol",
                  "filename_short": "contracts/AquaToken.sol",
                  "is_dependency": false,
                  "lines": [
                    13,
                    14,
                    15,
                    16,
                    17,
                    18,
                    19,
                    20,
                    21,
                    22,
                    23,
                    24,
                    25,
                    26,
                    27,
                    28,
                    29,
                    30,
                    31,
                    32,
                    33,
                    34,
                    35,
                    36,
                    37,
                    38,
                    39,
                    40,
                    41,
                    42,
                    43,
                    44,
                    45,
                    46,
                    47,
                    48,
                    49,
                    50,
                    51,
                    52,
                    53,
                    54,
                    55,
                    56,
                    57,
                    58,
                    59,
                    60,
                    61,
                    62,
                    63,
                    64,
                    65,
                    66,
                    67,
                    68,
                    69,
                    70,
                    71,
                    72,
                    73,
                    74,
                    75,
                    76,
                    77,
                    78,
                    79,
                    80,
                    81,
                    82,
                    83,
                    84,
                    85,
                    86,
                    87,
                    88,
                    89,
                    90,
                    91,
                    92,
                    93,
                    94,
                    95,
                    96,
                    97,
                    98,
                    99,
                    100,
                    101,
                    102,
                    103,
                    104,
                    105,
                    106,
                    107,
                    108,
                    109,
                    110,
                    111,
                    112,
                    113,
                    114,
                    115,
                    116,
                    117,
                    118,
                    119,
                    120,
                    121,
                    122,
                    123,
                    124,
                    125,
                    126,
                    127,
                    128,
                    129,
                    130,
                    131,
                    132,
                    133,
                    134,
                    135,
                    136,
                    137,
                    138,
                    139,
                    140,
                    141,
                    142,
                    143,
                    144,
                    145,
                    146,
                    147,
                    148,
                    149,
                    150,
                    151,
                    152,
                    153,
                    154,
                    155,
                    156,
                    157,
                    158,
                    159,
                    160,
                    161,
                    162,
                    163,
                    164,
                    165,
                    166,
                    167,
                    168,
                    169,
                    170,
                    171,
                    172,
                    173,
                    174,
                    175,
                    176,
                    177,
                    178,
                    179,
                    180,
                    181,
                    182,
                    183,
                    184,
                    185,
                    186,
                    187,
                    188,
                    189,
                    190,
                    191,
                    192,
                    193,
                    194,
                    195,
                    196,
                    197,
                    198,
                    199,
                    200
                  ],
                  "starting_column": 1,
                  "ending_column": 2
                }
              },
              "signature": "permit(address,address,uint256,uint256,uint8,bytes32,bytes32)"
            }
          }
        ],
        "description": "AquaToken.permit(address,address,uint256,uint256,uint8,bytes32,bytes32) (contracts/AquaToken.sol#157-173) uses keccak256(bytes)\n",
        "markdown": "[AquaToken.permit(address,address,uint256,uint256,uint8,bytes32,bytes32)](crytic-export/etherscan-contracts/0xd34a24006b862f4e9936c506691539d6433ad297-AquaToken/contracts/AquaToken.sol#L157-L173) uses keccak256(bytes)\n",
        "first_markdown_element": "crytic-export/etherscan-contracts/0xd34a24006b862f4e9936c506691539d6433ad297-AquaToken/contracts/AquaToken.sol#L157-L173",
        "id": "16115f6caa2020192d3bfaf31a4b53978e7d5795fd83dcc69d056e8353f268b9",
        "check": "crypto",
        "impact": "High",
        "confidence": "High"
      },
      {
        "elements": [
          {
            "type": "function",
            "name": "slitherConstructorConstantVariables",
            "source_mapping": {
              "start": 433,
              "length": 6780,
              "filename_relative": "crytic-export/etherscan-contracts/0xd34a24006b862f4e9936c506691539d6433ad297-AquaToken/contracts/AquaToken.sol",
              "filename_absolute": "/mnt/c/Users/zzs/Desktop/CrySol_Static/crytic-export/etherscan-contracts/0xd34a24006b862f4e9936c506691539d6433ad297-AquaToken/contracts/AquaToken.sol",
              "filename_short": "contracts/AquaToken.sol",
              "is_dependency": false,
              "lines": [
                13,
                14,
                15,
                16,
                17,
                18,
                19,
                20,
                21,
                22,
                23,
                24,
                25,
                26,
                27,
                28,
                29,
                30,
                31,
                32,
                33,
                34,
                35,
                36,
                37,
                38,
                39,
                40,
                41,
                42,
                43,
                44,
                45,
                46,
                47,
                48,
                49,
                50,
                51,
                52,
                53,
                54,
                55,
                56,
                57,
                58,
                59,
                60,
                61,
                62,
                63,
                64,
                65,
                66,
                67,
                68,
                69,
                70,
                71,
                72,
                73,
                74,
                75,
                76,
                77,
                78,
                79,
                80,
                81,
                82,
                83,
                84,
                85,
                86,
                87,
                88,
                89,
                90,
                91,
                92,
                93,
                94,
                95,
                96,
                97,
                98,
                99,
                100,
                101,
                102,
                103,
                104,
                105,
                106,
                107,
                108,
                109,
                110,
                111,
                112,
                113,
                114,
                115,
                116,
                117,
                118,
                119,
                120,
                121,
                122,
                123,
                124,
                125,
                126,
                127,
                128,
                129,
                130,
                131,
                132,
                133,
                134,
                135,
                136,
                137,
                138,
                139,
                140,
                141,
                142,
                143,
                144,
                145,
                146,
                147,
                148,
                149,
                150,
                151,
                152,
                153,
                154,
                155,
                156,
                157,
                158,
                159,
                160,
                161,
                162,
                163,
                164,
                165,
                166,
                167,
                168,
                169,
                170,
                171,
                172,
                173,
                174,
                175,
                176,
                177,
                178,
                179,
                180,
                181,
                182,
                183,
                184,
                185,
                186,
                187,
                188,
                189,
                190,
                191,
                192,
                193,
                194,
                195,
                196,
                197,
                198,
                199,
                200
              ],
              "starting_column": 1,
              "ending_column": 2
            },
            "type_specific_fields": {
              "parent": {
                "type": "contract",
                "name": "AquaToken",
                "source_mapping": {
                  "start": 433,
                  "length": 6780,
                  "filename_relative": "crytic-export/etherscan-contracts/0xd34a24006b862f4e9936c506691539d6433ad297-AquaToken/contracts/AquaToken.sol",
                  "filename_absolute": "/mnt/c/Users/zzs/Desktop/CrySol_Static/crytic-export/etherscan-contracts/0xd34a24006b862f4e9936c506691539d6433ad297-AquaToken/contracts/AquaToken.sol",
                  "filename_short": "contracts/AquaToken.sol",
                  "is_dependency": false,
                  "lines": [
                    13,
                    14,
                    15,
                    16,
                    17,
                    18,
                    19,
                    20,
                    21,
                    22,
                    23,
                    24,
                    25,
                    26,
                    27,
                    28,
                    29,
                    30,
                    31,
                    32,
                    33,
                    34,
                    35,
                    36,
                    37,
                    38,
                    39,
                    40,
                    41,
                    42,
                    43,
                    44,
                    45,
                    46,
                    47,
                    48,
                    49,
                    50,
                    51,
                    52,
                    53,
                    54,
                    55,
                    56,
                    57,
                    58,
                    59,
                    60,
                    61,
                    62,
                    63,
                    64,
                    65,
                    66,
                    67,
                    68,
                    69,
                    70,
                    71,
                    72,
                    73,
                    74,
                    75,
                    76,
                    77,
                    78,
                    79,
                    80,
                    81,
                    82,
                    83,
                    84,
                    85,
                    86,
                    87,
                    88,
                    89,
                    90,
                    91,
                    92,
                    93,
                    94,
                    95,
                    96,
                    97,
                    98,
                    99,
                    100,
                    101,
                    102,
                    103,
                    104,
                    105,
                    106,
                    107,
                    108,
                    109,
                    110,
                    111,
                    112,
                    113,
                    114,
                    115,
                    116,
                    117,
                    118,
                    119,
                    120,
                    121,
                    122,
                    123,
                    124,
                    125,
                    126,
                    127,
                    128,
                    129,
                    130,
                    131,
                    132,
                    133,
                    134,
                    135,
                    136,
                    137,
                    138,
                    139,
                    140,
                    141,
                    142,
                    143,
                    144,
                    145,
                    146,
                    147,
                    148,
                    149,
                    150,
                    151,
                    152,
                    153,
                    154,
                    155,
                    156,
                    157,
                    158,
                    159,
                    160,
                    161,
                    162,
                    163,
                    164,
                    165,
                    166,
                    167,
                    168,
                    169,
                    170,
                    171,
                    172,
                    173,
                    174,
                    175,
                    176,
                    177,
                    178,
                    179,
                    180,
                    181,
                    182,
                    183,
                    184,
                    185,
                    186,
                    187,
                    188,
                    189,
                    190,
                    191,
                    192,
                    193,
                    194,
                    195,
                    196,
                    197,
                    198,
                    199,
                    200
                  ],
                  "starting_column": 1,
                  "ending_column": 2
                }
              },
              "signature": "slitherConstructorConstantVariables()"
            }
          }
        ],
        "description": "AquaToken.slitherConstructorConstantVariables() (contracts/AquaToken.sol#13-200) uses keccak256(bytes)\n",
        "markdown": "[AquaToken.slitherConstructorConstantVariables()](crytic-export/etherscan-contracts/0xd34a24006b862f4e9936c506691539d6433ad297-AquaToken/contracts/AquaToken.sol#L13-L200) uses keccak256(bytes)\n",
        "first_markdown_element": "crytic-export/etherscan-contracts/0xd34a24006b862f4e9936c506691539d6433ad297-AquaToken/contracts/AquaToken.sol#L13-L200",
        "id": "7e9f44fa7c5844588a6a496489712343cf3228143500d14062b778086a18274f",
        "check": "crypto",
        "impact": "High",
        "confidence": "High"
      },
      {
        "elements": [
          {
            "type": "function",
            "name": "_validateSignedData",
            "source_mapping": {
              "start": 2560,
              "length": 438,
              "filename_relative": "crytic-export/etherscan-contracts/0xd34a24006b862f4e9936c506691539d6433ad297-AquaToken/contracts/AquaToken.sol",
              "filename_absolute": "/mnt/c/Users/zzs/Desktop/CrySol_Static/crytic-export/etherscan-contracts/0xd34a24006b862f4e9936c506691539d6433ad297-AquaToken/contracts/AquaToken.sol",
              "filename_short": "contracts/AquaToken.sol",
              "is_dependency": false,
              "lines": [
                57,
                58,
                59,
                60,
                61,
                62,
                63,
                64,
                65,
                66,
                67
              ],
              "starting_column": 5,
              "ending_column": 6
            },
            "type_specific_fields": {
              "parent": {
                "type": "contract",
                "name": "AquaToken",
                "source_mapping": {
                  "start": 433,
                  "length": 6780,
                  "filename_relative": "crytic-export/etherscan-contracts/0xd34a24006b862f4e9936c506691539d6433ad297-AquaToken/contracts/AquaToken.sol",
                  "filename_absolute": "/mnt/c/Users/zzs/Desktop/CrySol_Static/crytic-export/etherscan-contracts/0xd34a24006b862f4e9936c506691539d6433ad297-AquaToken/contracts/AquaToken.sol",
                  "filename_short": "contracts/AquaToken.sol",
                  "is_dependency": false,
                  "lines": [
                    13,
                    14,
                    15,
                    16,
                    17,
                    18,
                    19,
                    20,
                    21,
                    22,
                    23,
                    24,
                    25,
                    26,
                    27,
                    28,
                    29,
                    30,
                    31,
                    32,
                    33,
                    34,
                    35,
                    36,
                    37,
                    38,
                    39,
                    40,
                    41,
                    42,
                    43,
                    44,
                    45,
                    46,
                    47,
                    48,
                    49,
                    50,
                    51,
                    52,
                    53,
                    54,
                    55,
                    56,
                    57,
                    58,
                    59,
                    60,
                    61,
                    62,
                    63,
                    64,
                    65,
                    66,
                    67,
                    68,
                    69,
                    70,
                    71,
                    72,
                    73,
                    74,
                    75,
                    76,
                    77,
                    78,
                    79,
                    80,
                    81,
                    82,
                    83,
                    84,
                    85,
                    86,
                    87,
                    88,
                    89,
                    90,
                    91,
                    92,
                    93,
                    94,
                    95,
                    96,
                    97,
                    98,
                    99,
                    100,
                    101,
                    102,
                    103,
                    104,
                    105,
                    106,
                    107,
                    108,
                    109,
                    110,
                    111,
                    112,
                    113,
                    114,
                    115,
                    116,
                    117,
                    118,
                    119,
                    120,
                    121,
                    122,
                    123,
                    124,
                    125,
                    126,
                    127,
                    128,
                    129,
                    130,
                    131,
                    132,
                    133,
                    134,
                    135,
                    136,
                    137,
                    138,
                    139,
                    140,
                    141,
                    142,
                    143,
                    144,
                    145,
                    146,
                    147,
                    148,
                    149,
                    150,
                    151,
                    152,
                    153,
                    154,
                    155,
                    156,
                    157,
                    158,
                    159,
                    160,
                    161,
                    162,
                    163,
                    164,
                    165,
                    166,
                    167,
                    168,
                    169,
                    170,
                    171,
                    172,
                    173,
                    174,
                    175,
                    176,
                    177,
                    178,
                    179,
                    180,
                    181,
                    182,
                    183,
                    184,
                    185,
                    186,
                    187,
                    188,
                    189,
                    190,
                    191,
                    192,
                    193,
                    194,
                    195,
                    196,
                    197,
                    198,
                    199,
                    200
                  ],
                  "starting_column": 1,
                  "ending_column": 2
                }
              },
              "signature": "_validateSignedData(address,bytes32,uint8,bytes32,bytes32)"
            }
          }
        ],
        "description": "AquaToken._validateSignedData(address,bytes32,uint8,bytes32,bytes32) (contracts/AquaToken.sol#57-67) uses keccak256(bytes)\n",
        "markdown": "[AquaToken._validateSignedData(address,bytes32,uint8,bytes32,bytes32)](crytic-export/etherscan-contracts/0xd34a24006b862f4e9936c506691539d6433ad297-AquaToken/contracts/AquaToken.sol#L57-L67) uses keccak256(bytes)\n",
        "first_markdown_element": "crytic-export/etherscan-contracts/0xd34a24006b862f4e9936c506691539d6433ad297-AquaToken/contracts/AquaToken.sol#L57-L67",
        "id": "8e87df2bb0071c234531e5a04a741bc8d9f5581acde67bdf65ea4fe6d86364d7",
        "check": "crypto",
        "impact": "High",
        "confidence": "High"
      },
      {
        "elements": [
          {
            "type": "function",
            "name": "_validateSignedData",
            "source_mapping": {
              "start": 2560,
              "length": 438,
              "filename_relative": "crytic-export/etherscan-contracts/0xd34a24006b862f4e9936c506691539d6433ad297-AquaToken/contracts/AquaToken.sol",
              "filename_absolute": "/mnt/c/Users/zzs/Desktop/CrySol_Static/crytic-export/etherscan-contracts/0xd34a24006b862f4e9936c506691539d6433ad297-AquaToken/contracts/AquaToken.sol",
              "filename_short": "contracts/AquaToken.sol",
              "is_dependency": false,
              "lines": [
                57,
                58,
                59,
                60,
                61,
                62,
                63,
                64,
                65,
                66,
                67
              ],
              "starting_column": 5,
              "ending_column": 6
            },
            "type_specific_fields": {
              "parent": {
                "type": "contract",
                "name": "AquaToken",
                "source_mapping": {
                  "start": 433,
                  "length": 6780,
                  "filename_relative": "crytic-export/etherscan-contracts/0xd34a24006b862f4e9936c506691539d6433ad297-AquaToken/contracts/AquaToken.sol",
                  "filename_absolute": "/mnt/c/Users/zzs/Desktop/CrySol_Static/crytic-export/etherscan-contracts/0xd34a24006b862f4e9936c506691539d6433ad297-AquaToken/contracts/AquaToken.sol",
                  "filename_short": "contracts/AquaToken.sol",
                  "is_dependency": false,
                  "lines": [
                    13,
                    14,
                    15,
                    16,
                    17,
                    18,
                    19,
                    20,
                    21,
                    22,
                    23,
                    24,
                    25,
                    26,
                    27,
                    28,
                    29,
                    30,
                    31,
                    32,
                    33,
                    34,
                    35,
                    36,
                    37,
                    38,
                    39,
                    40,
                    41,
                    42,
                    43,
                    44,
                    45,
                    46,
                    47,
                    48,
                    49,
                    50,
                    51,
                    52,
                    53,
                    54,
                    55,
                    56,
                    57,
                    58,
                    59,
                    60,
                    61,
                    62,
                    63,
                    64,
                    65,
                    66,
                    67,
                    68,
                    69,
                    70,
                    71,
                    72,
                    73,
                    74,
                    75,
                    76,
                    77,
                    78,
                    79,
                    80,
                    81,
                    82,
                    83,
                    84,
                    85,
                    86,
                    87,
                    88,
                    89,
                    90,
                    91,
                    92,
                    93,
                    94,
                    95,
                    96,
                    97,
                    98,
                    99,
                    100,
                    101,
                    102,
                    103,
                    104,
                    105,
                    106,
                    107,
                    108,
                    109,
                    110,
                    111,
                    112,
                    113,
                    114,
                    115,
                    116,
                    117,
                    118,
                    119,
                    120,
                    121,
                    122,
                    123,
                    124,
                    125,
                    126,
                    127,
                    128,
                    129,
                    130,
                    131,
                    132,
                    133,
                    134,
                    135,
                    136,
                    137,
                    138,
                    139,
                    140,
                    141,
                    142,
                    143,
                    144,
                    145,
                    146,
                    147,
                    148,
                    149,
                    150,
                    151,
                    152,
                    153,
                    154,
                    155,
                    156,
                    157,
                    158,
                    159,
                    160,
                    161,
                    162,
                    163,
                    164,
                    165,
                    166,
                    167,
                    168,
                    169,
                    170,
                    171,
                    172,
                    173,
                    174,
                    175,
                    176,
                    177,
                    178,
                    179,
                    180,
                    181,
                    182,
                    183,
                    184,
                    185,
                    186,
                    187,
                    188,
                    189,
                    190,
                    191,
                    192,
                    193,
                    194,
                    195,
                    196,
                    197,
                    198,
                    199,
                    200
                  ],
                  "starting_column": 1,
                  "ending_column": 2
                }
              },
              "signature": "_validateSignedData(address,bytes32,uint8,bytes32,bytes32)"
            }
          }
        ],
        "description": "AquaToken._validateSignedData(address,bytes32,uint8,bytes32,bytes32) (contracts/AquaToken.sol#57-67) uses ecrecover(bytes32,uint8,bytes32,bytes32)\n",
        "markdown": "[AquaToken._validateSignedData(address,bytes32,uint8,bytes32,bytes32)](crytic-export/etherscan-contracts/0xd34a24006b862f4e9936c506691539d6433ad297-AquaToken/contracts/AquaToken.sol#L57-L67) uses ecrecover(bytes32,uint8,bytes32,bytes32)\n",
        "first_markdown_element": "crytic-export/etherscan-contracts/0xd34a24006b862f4e9936c506691539d6433ad297-AquaToken/contracts/AquaToken.sol#L57-L67",
        "id": "c15beb3faeb3252127602f09e99910a859133e74a64ad1e911327c230b9d3201",
        "check": "crypto",
        "impact": "High",
        "confidence": "High"
      },
      {
        "elements": [
          {
            "type": "function",
            "name": "transferWithAuthorization",
            "source_mapping": {
              "start": 6364,
              "length": 847,
              "filename_relative": "crytic-export/etherscan-contracts/0xd34a24006b862f4e9936c506691539d6433ad297-AquaToken/contracts/AquaToken.sol",
              "filename_absolute": "/mnt/c/Users/zzs/Desktop/CrySol_Static/crytic-export/etherscan-contracts/0xd34a24006b862f4e9936c506691539d6433ad297-AquaToken/contracts/AquaToken.sol",
              "filename_short": "contracts/AquaToken.sol",
              "is_dependency": false,
              "lines": [
                175,
                176,
                177,
                178,
                179,
                180,
                181,
                182,
                183,
                184,
                185,
                186,
                187,
                188,
                189,
                190,
                191,
                192,
                193,
                194,
                195,
                196,
                197,
                198,
                199
              ],
              "starting_column": 5,
              "ending_column": 6
            },
            "type_specific_fields": {
              "parent": {
                "type": "contract",
                "name": "AquaToken",
                "source_mapping": {
                  "start": 433,
                  "length": 6780,
                  "filename_relative": "crytic-export/etherscan-contracts/0xd34a24006b862f4e9936c506691539d6433ad297-AquaToken/contracts/AquaToken.sol",
                  "filename_absolute": "/mnt/c/Users/zzs/Desktop/CrySol_Static/crytic-export/etherscan-contracts/0xd34a24006b862f4e9936c506691539d6433ad297-AquaToken/contracts/AquaToken.sol",
                  "filename_short": "contracts/AquaToken.sol",
                  "is_dependency": false,
                  "lines": [
                    13,
                    14,
                    15,
                    16,
                    17,
                    18,
                    19,
                    20,
                    21,
                    22,
                    23,
                    24,
                    25,
                    26,
                    27,
                    28,
                    29,
                    30,
                    31,
                    32,
                    33,
                    34,
                    35,
                    36,
                    37,
                    38,
                    39,
                    40,
                    41,
                    42,
                    43,
                    44,
                    45,
                    46,
                    47,
                    48,
                    49,
                    50,
                    51,
                    52,
                    53,
                    54,
                    55,
                    56,
                    57,
                    58,
                    59,
                    60,
                    61,
                    62,
                    63,
                    64,
                    65,
                    66,
                    67,
                    68,
                    69,
                    70,
                    71,
                    72,
                    73,
                    74,
                    75,
                    76,
                    77,
                    78,
                    79,
                    80,
                    81,
                    82,
                    83,
                    84,
                    85,
                    86,
                    87,
                    88,
                    89,
                    90,
                    91,
                    92,
                    93,
                    94,
                    95,
                    96,
                    97,
                    98,
                    99,
                    100,
                    101,
                    102,
                    103,
                    104,
                    105,
                    106,
                    107,
                    108,
                    109,
                    110,
                    111,
                    112,
                    113,
                    114,
                    115,
                    116,
                    117,
                    118,
                    119,
                    120,
                    121,
                    122,
                    123,
                    124,
                    125,
                    126,
                    127,
                    128,
                    129,
                    130,
                    131,
                    132,
                    133,
                    134,
                    135,
                    136,
                    137,
                    138,
                    139,
                    140,
                    141,
                    142,
                    143,
                    144,
                    145,
                    146,
                    147,
                    148,
                    149,
                    150,
                    151,
                    152,
                    153,
                    154,
                    155,
                    156,
                    157,
                    158,
                    159,
                    160,
                    161,
                    162,
                    163,
                    164,
                    165,
                    166,
                    167,
                    168,
                    169,
                    170,
                    171,
                    172,
                    173,
                    174,
                    175,
                    176,
                    177,
                    178,
                    179,
                    180,
                    181,
                    182,
                    183,
                    184,
                    185,
                    186,
                    187,
                    188,
                    189,
                    190,
                    191,
                    192,
                    193,
                    194,
                    195,
                    196,
                    197,
                    198,
                    199,
                    200
                  ],
                  "starting_column": 1,
                  "ending_column": 2
                }
              },
              "signature": "transferWithAuthorization(address,address,uint256,uint256,uint256,bytes32,uint8,bytes32,bytes32)"
            }
          }
        ],
        "description": "AquaToken.transferWithAuthorization(address,address,uint256,uint256,uint256,bytes32,uint8,bytes32,bytes32) (contracts/AquaToken.sol#175-199) uses keccak256(bytes)\n",
        "markdown": "[AquaToken.transferWithAuthorization(address,address,uint256,uint256,uint256,bytes32,uint8,bytes32,bytes32)](crytic-export/etherscan-contracts/0xd34a24006b862f4e9936c506691539d6433ad297-AquaToken/contracts/AquaToken.sol#L175-L199) uses keccak256(bytes)\n",
        "first_markdown_element": "crytic-export/etherscan-contracts/0xd34a24006b862f4e9936c506691539d6433ad297-AquaToken/contracts/AquaToken.sol#L175-L199",
        "id": "cf2e91a376db0867574f89b52ded2295984d59c34c506382c6ceb3601034b009",
        "check": "crypto",
        "impact": "High",
        "confidence": "High"
      },
      {
        "elements": [
          {
            "type": "function",
            "name": "permit",
            "source_mapping": {
              "start": 5834,
              "length": 524,
              "filename_relative": "crytic-export/etherscan-contracts/0xd34a24006b862f4e9936c506691539d6433ad297-AquaToken/contracts/AquaToken.sol",
              "filename_absolute": "/mnt/c/Users/zzs/Desktop/CrySol_Static/crytic-export/etherscan-contracts/0xd34a24006b862f4e9936c506691539d6433ad297-AquaToken/contracts/AquaToken.sol",
              "filename_short": "contracts/AquaToken.sol",
              "is_dependency": false,
              "lines": [
                157,
                158,
                159,
                160,
                161,
                162,
                163,
                164,
                165,
                166,
                167,
                168,
                169,
                170,
                171,
                172,
                173
              ],
              "starting_column": 5,
              "ending_column": 6
            },
            "type_specific_fields": {
              "parent": {
                "type": "contract",
                "name": "AquaToken",
                "source_mapping": {
                  "start": 433,
                  "length": 6780,
                  "filename_relative": "crytic-export/etherscan-contracts/0xd34a24006b862f4e9936c506691539d6433ad297-AquaToken/contracts/AquaToken.sol",
                  "filename_absolute": "/mnt/c/Users/zzs/Desktop/CrySol_Static/crytic-export/etherscan-contracts/0xd34a24006b862f4e9936c506691539d6433ad297-AquaToken/contracts/AquaToken.sol",
                  "filename_short": "contracts/AquaToken.sol",
                  "is_dependency": false,
                  "lines": [
                    13,
                    14,
                    15,
                    16,
                    17,
                    18,
                    19,
                    20,
                    21,
                    22,
                    23,
                    24,
                    25,
                    26,
                    27,
                    28,
                    29,
                    30,
                    31,
                    32,
                    33,
                    34,
                    35,
                    36,
                    37,
                    38,
                    39,
                    40,
                    41,
                    42,
                    43,
                    44,
                    45,
                    46,
                    47,
                    48,
                    49,
                    50,
                    51,
                    52,
                    53,
                    54,
                    55,
                    56,
                    57,
                    58,
                    59,
                    60,
                    61,
                    62,
                    63,
                    64,
                    65,
                    66,
                    67,
                    68,
                    69,
                    70,
                    71,
                    72,
                    73,
                    74,
                    75,
                    76,
                    77,
                    78,
                    79,
                    80,
                    81,
                    82,
                    83,
                    84,
                    85,
                    86,
                    87,
                    88,
                    89,
                    90,
                    91,
                    92,
                    93,
                    94,
                    95,
                    96,
                    97,
                    98,
                    99,
                    100,
                    101,
                    102,
                    103,
                    104,
                    105,
                    106,
                    107,
                    108,
                    109,
                    110,
                    111,
                    112,
                    113,
                    114,
                    115,
                    116,
                    117,
                    118,
                    119,
                    120,
                    121,
                    122,
                    123,
                    124,
                    125,
                    126,
                    127,
                    128,
                    129,
                    130,
                    131,
                    132,
                    133,
                    134,
                    135,
                    136,
                    137,
                    138,
                    139,
                    140,
                    141,
                    142,
                    143,
                    144,
                    145,
                    146,
                    147,
                    148,
                    149,
                    150,
                    151,
                    152,
                    153,
                    154,
                    155,
                    156,
                    157,
                    158,
                    159,
                    160,
                    161,
                    162,
                    163,
                    164,
                    165,
                    166,
                    167,
                    168,
                    169,
                    170,
                    171,
                    172,
                    173,
                    174,
                    175,
                    176,
                    177,
                    178,
                    179,
                    180,
                    181,
                    182,
                    183,
                    184,
                    185,
                    186,
                    187,
                    188,
                    189,
                    190,
                    191,
                    192,
                    193,
                    194,
                    195,
                    196,
                    197,
                    198,
                    199,
                    200
                  ],
                  "starting_column": 1,
                  "ending_column": 2
                }
              },
              "signature": "permit(address,address,uint256,uint256,uint8,bytes32,bytes32)"
            }
          }
        ],
        "description": "AquaToken.permit(address,address,uint256,uint256,uint8,bytes32,bytes32) (contracts/AquaToken.sol#157-173)does not contains protect against signature malleability ",
        "markdown": "[AquaToken.permit(address,address,uint256,uint256,uint8,bytes32,bytes32)](crytic-export/etherscan-contracts/0xd34a24006b862f4e9936c506691539d6433ad297-AquaToken/contracts/AquaToken.sol#L157-L173)does not contains protect against signature malleability ",
        "first_markdown_element": "crytic-export/etherscan-contracts/0xd34a24006b862f4e9936c506691539d6433ad297-AquaToken/contracts/AquaToken.sol#L157-L173",
        "id": "35d6744739a5f786df32aa2fb304c556afed5a112f69f7e01589472694010a94",
        "check": "sig-mal",
        "impact": "High",
        "confidence": "High"
      },
      {
        "elements": [
          {
            "type": "function",
            "name": "transferWithAuthorization",
            "source_mapping": {
              "start": 6364,
              "length": 847,
              "filename_relative": "crytic-export/etherscan-contracts/0xd34a24006b862f4e9936c506691539d6433ad297-AquaToken/contracts/AquaToken.sol",
              "filename_absolute": "/mnt/c/Users/zzs/Desktop/CrySol_Static/crytic-export/etherscan-contracts/0xd34a24006b862f4e9936c506691539d6433ad297-AquaToken/contracts/AquaToken.sol",
              "filename_short": "contracts/AquaToken.sol",
              "is_dependency": false,
              "lines": [
                175,
                176,
                177,
                178,
                179,
                180,
                181,
                182,
                183,
                184,
                185,
                186,
                187,
                188,
                189,
                190,
                191,
                192,
                193,
                194,
                195,
                196,
                197,
                198,
                199
              ],
              "starting_column": 5,
              "ending_column": 6
            },
            "type_specific_fields": {
              "parent": {
                "type": "contract",
                "name": "AquaToken",
                "source_mapping": {
                  "start": 433,
                  "length": 6780,
                  "filename_relative": "crytic-export/etherscan-contracts/0xd34a24006b862f4e9936c506691539d6433ad297-AquaToken/contracts/AquaToken.sol",
                  "filename_absolute": "/mnt/c/Users/zzs/Desktop/CrySol_Static/crytic-export/etherscan-contracts/0xd34a24006b862f4e9936c506691539d6433ad297-AquaToken/contracts/AquaToken.sol",
                  "filename_short": "contracts/AquaToken.sol",
                  "is_dependency": false,
                  "lines": [
                    13,
                    14,
                    15,
                    16,
                    17,
                    18,
                    19,
                    20,
                    21,
                    22,
                    23,
                    24,
                    25,
                    26,
                    27,
                    28,
                    29,
                    30,
                    31,
                    32,
                    33,
                    34,
                    35,
                    36,
                    37,
                    38,
                    39,
                    40,
                    41,
                    42,
                    43,
                    44,
                    45,
                    46,
                    47,
                    48,
                    49,
                    50,
                    51,
                    52,
                    53,
                    54,
                    55,
                    56,
                    57,
                    58,
                    59,
                    60,
                    61,
                    62,
                    63,
                    64,
                    65,
                    66,
                    67,
                    68,
                    69,
                    70,
                    71,
                    72,
                    73,
                    74,
                    75,
                    76,
                    77,
                    78,
                    79,
                    80,
                    81,
                    82,
                    83,
                    84,
                    85,
                    86,
                    87,
                    88,
                    89,
                    90,
                    91,
                    92,
                    93,
                    94,
                    95,
                    96,
                    97,
                    98,
                    99,
                    100,
                    101,
                    102,
                    103,
                    104,
                    105,
                    106,
                    107,
                    108,
                    109,
                    110,
                    111,
                    112,
                    113,
                    114,
                    115,
                    116,
                    117,
                    118,
                    119,
                    120,
                    121,
                    122,
                    123,
                    124,
                    125,
                    126,
                    127,
                    128,
                    129,
                    130,
                    131,
                    132,
                    133,
                    134,
                    135,
                    136,
                    137,
                    138,
                    139,
                    140,
                    141,
                    142,
                    143,
                    144,
                    145,
                    146,
                    147,
                    148,
                    149,
                    150,
                    151,
                    152,
                    153,
                    154,
                    155,
                    156,
                    157,
                    158,
                    159,
                    160,
                    161,
                    162,
                    163,
                    164,
                    165,
                    166,
                    167,
                    168,
                    169,
                    170,
                    171,
                    172,
                    173,
                    174,
                    175,
                    176,
                    177,
                    178,
                    179,
                    180,
                    181,
                    182,
                    183,
                    184,
                    185,
                    186,
                    187,
                    188,
                    189,
                    190,
                    191,
                    192,
                    193,
                    194,
                    195,
                    196,
                    197,
                    198,
                    199,
                    200
                  ],
                  "starting_column": 1,
                  "ending_column": 2
                }
              },
              "signature": "transferWithAuthorization(address,address,uint256,uint256,uint256,bytes32,uint8,bytes32,bytes32)"
            }
          }
        ],
        "description": "AquaToken.transferWithAuthorization(address,address,uint256,uint256,uint256,bytes32,uint8,bytes32,bytes32) (contracts/AquaToken.sol#175-199)does not contains protect against signature malleability ",
        "markdown": "[AquaToken.transferWithAuthorization(address,address,uint256,uint256,uint256,bytes32,uint8,bytes32,bytes32)](crytic-export/etherscan-contracts/0xd34a24006b862f4e9936c506691539d6433ad297-AquaToken/contracts/AquaToken.sol#L175-L199)does not contains protect against signature malleability ",
        "first_markdown_element": "crytic-export/etherscan-contracts/0xd34a24006b862f4e9936c506691539d6433ad297-AquaToken/contracts/AquaToken.sol#L175-L199",
        "id": "6f96aef7d6dcfe76dfad6dd6748d24bc4fefeea957868453daf6b6956019df1a",
        "check": "sig-mal",
        "impact": "High",
        "confidence": "High"
      }
    ]
  }
}