{
  "success": true,
  "error": null,
  "results": {
    "detectors": [
      {
        "elements": [
          {
            "type": "function",
            "name": "approveAndCall",
            "source_mapping": {
              "start": 8361,
              "length": 794,
              "filename_relative": "crytic-export/etherscan-contracts/0xec1b7eb3d3cfac7027fa60b5376e5eadef4f1300-HZMCOIN.sol",
              "filename_absolute": "/mnt/c/Users/zzs/Desktop/CrySol_Static/crytic-export/etherscan-contracts/0xec1b7eb3d3cfac7027fa60b5376e5eadef4f1300-HZMCOIN.sol",
              "filename_short": "crytic-export/etherscan-contracts/0xec1b7eb3d3cfac7027fa60b5376e5eadef4f1300-HZMCOIN.sol",
              "is_dependency": false,
              "lines": [
                213,
                214,
                215,
                216,
                217,
                218,
                219,
                220,
                221,
                222
              ],
              "starting_column": 5,
              "ending_column": 6
            },
            "type_specific_fields": {
              "parent": {
                "type": "contract",
                "name": "HZMCOIN",
                "source_mapping": {
                  "start": 7360,
                  "length": 1798,
                  "filename_relative": "crytic-export/etherscan-contracts/0xec1b7eb3d3cfac7027fa60b5376e5eadef4f1300-HZMCOIN.sol",
                  "filename_absolute": "/mnt/c/Users/zzs/Desktop/CrySol_Static/crytic-export/etherscan-contracts/0xec1b7eb3d3cfac7027fa60b5376e5eadef4f1300-HZMCOIN.sol",
                  "filename_short": "crytic-export/etherscan-contracts/0xec1b7eb3d3cfac7027fa60b5376e5eadef4f1300-HZMCOIN.sol",
                  "is_dependency": false,
                  "lines": [
                    192,
                    193,
                    194,
                    195,
                    196,
                    197,
                    198,
                    199,
                    200,
                    201,
                    202,
                    203,
                    204,
                    205,
                    206,
                    207,
                    208,
                    209,
                    210,
                    211,
                    212,
                    213,
                    214,
                    215,
                    216,
                    217,
                    218,
                    219,
                    220,
                    221,
                    222,
                    223,
                    224
                  ],
                  "starting_column": 1,
                  "ending_column": 0
                }
              },
              "signature": "approveAndCall(address,uint256,bytes)"
            }
          }
        ],
        "description": "HZMCOIN.approveAndCall(address,uint256,bytes) (crytic-export/etherscan-contracts/0xec1b7eb3d3cfac7027fa60b5376e5eadef4f1300-HZMCOIN.sol#213-222) uses sha3()\n",
        "markdown": "[HZMCOIN.approveAndCall(address,uint256,bytes)](crytic-export/etherscan-contracts/0xec1b7eb3d3cfac7027fa60b5376e5eadef4f1300-HZMCOIN.sol#L213-L222) uses sha3()\n",
        "first_markdown_element": "crytic-export/etherscan-contracts/0xec1b7eb3d3cfac7027fa60b5376e5eadef4f1300-HZMCOIN.sol#L213-L222",
        "id": "617c1855d98fbedd345fba1eef98f73645a42b5a87ba800e6f2bca6e304aa66d",
        "check": "crypto",
        "impact": "High",
        "confidence": "High"
      }
    ]
  }
}